ncep_client
