Metadata-Version: 1.1
Name: ncep-client
Version: 1.1.1
Summary: Communicates with NCEP product inventory servers and gets avaliable data.
Home-page: https://github.com/AaronV77/NCEP_Data_Grabber
Author: Aaron Valoroso
Author-email: valoroso99@gmail.com
License: BSD License
Keywords: ncep,product inventory
Platform: UNKNOWN
Classifier: Development Status :: 4 - Beta
Classifier: Intended Audience :: Developers
Classifier: Topic :: Software Development :: Build Tools
Classifier: License :: OSI Approved :: BSD License
Classifier: Programming Language :: Python :: 3.6
